{"id":"1317353c-e8ff-4781-82d5-34ecf8028eca","board_compatibility":["SENSOR_TILE_BOX_PRO"],"description":"usbflow","notes":"","sensors":[{"id":"S1","description":"Temperature sensor","icon":"ic_termometer","output":"Temperature","outputs":["O1","O2","O3"],"model":"STTS22H","dataType":"Float scalar","um":"degC","datasheetLink":"https://www.st.com/resource/en/datasheet/stts22h.pdf","powerModes":[{"minCustomOdr":1.0,"label":"Power Mode","odrs":[1.0,25.0,50.0,100.0]}],"acquisitionTime":0.0,"board_compatibility":["SENSOR_TILE_BOX_PRO","SENSOR_TILE_BOX_PROB"],"configuration":{"odr":1.0,"powerMode":"NONE","acquisitionTime":0.0}},{"id":"S5","description":"Accelerometer sensor","icon":"ic_inemo","output":"Acceleration","outputs":["O1","O2","O3"],"model":"LSM6DSV16X","dataType":"Float vector x3","um":"mg","fullScaleUm":"g","datasheetLink":"https://www.st.com/resource/en/datasheet/lsm6dsv16x.pdf","fullScales":[2,4,8,16],"powerModes":[{"mode":"LOW_POWER","label":"Low power","odrs":[1.875,7.5,15.0,30.0,60.0,120.0,240.0,480.0,960.0,1920.0]},{"mode":"HIGH_PERFORMANCE","label":"High performance","odrs":[7.5,15.0,30.0,60.0,120.0,240.0,480.0,960.0,1920.0,3840.0,7680.0]}],"acquisitionTime":0.0,"bleMaxOdr":60.0,"board_compatibility":["SENSOR_TILE_BOX_PRO","SENSOR_TILE_BOX_PROB"],"configuration":{"odr":60.0,"powerMode":"LOW_POWER","acquisitionTime":0.0,"filters":{"lowPass":{"label":"700","value":1}},"fullScale":2}},{"id":"S6","description":"Gyroscope sensor","icon":"ic_inemo","output":"Angular rate","outputs":["O1","O2","O3"],"model":"LSM6DSV16X","dataType":"Float vector x3","um":"mdps","fullScaleUm":"dps","datasheetLink":"https://www.st.com/resource/en/datasheet/lsm6dsv16x.pdf","fullScales":[125,250,500,1000,2000,4000],"powerModes":[{"mode":"LOW_POWER","label":"Low power","odrs":[7.5,15.0,30.0,60.0,120.0,240.0]},{"mode":"HIGH_PERFORMANCE","label":"High performance","odrs":[7.5,15.0,30.0,60.0,120.0,240.0,480.0,960.0,1920.0,3840.0,7680.0]}],"acquisitionTime":0.0,"bleMaxOdr":60.0,"board_compatibility":["SENSOR_TILE_BOX_PRO","SENSOR_TILE_BOX_PROB"],"configuration":{"odr":60.0,"powerMode":"LOW_POWER","acquisitionTime":0.0,"fullScale":2000}},{"id":"S8","description":"Magnetic field sensor","icon":"ic_magnetometer","output":"Magnetic field","outputs":["O1","O2","O3"],"model":"LIS2MDL","notes":"OFF_CANC always enabled","dataType":"Float vector x3","um":"mG","datasheetLink":"https://www.st.com/resource/en/datasheet/lis2mdl.pdf","powerModes":[{"mode":"LOW_POWER","label":"Low power","odrs":[10.0,20.0,50.0,100.0]},{"mode":"HIGH_RESOLUTION","label":"High resolution","odrs":[10.0,20.0,50.0,100.0]}],"acquisitionTime":0.0,"bleMaxOdr":50.0,"board_compatibility":["SENSOR_TILE_BOX","SENSOR_TILE_BOX_PRO","SENSOR_TILE_BOX_PROB"],"configuration":{"odr":50.0,"powerMode":"LOW_POWER","acquisitionTime":0.0}}],"outputs":[{"id":"O3","board_compatibility":["SENSOR_TILE_BOX","SENSOR_TILE_BOX_PRO","SENSOR_TILE_BOX_PROB"],"description":"Stream to Bluetooth","icon":"ic_bluetooth","properties":[]},{"id":"O2","board_compatibility":["SENSOR_TILE_BOX","SENSOR_TILE_BOX_PRO","SENSOR_TILE_BOX_PROB"],"description":"Stream to USB","icon":"ic_usb","properties":[]}]}